orm_right_version.py
orm_right_version-0.1.0.dist-info/WHEEL
orm_right_version-0.1.0.dist-info/METADATA
orm_right_version-0.1.0.dist-info/RECORD
